aerospike_vector_search/__init__.py
aerospike_vector_search/client.py
aerospike_vector_search/index.py
aerospike_vector_search/types.py
aerospike_vector_search/aio/__init__.py
aerospike_vector_search/aio/client.py
aerospike_vector_search/aio/index.py
aerospike_vector_search/aio/internal/channel_provider.py
aerospike_vector_search/internal/__init__.py
aerospike_vector_search/internal/channel_provider.py
aerospike_vector_search/shared/__init__.py
aerospike_vector_search/shared/admin_helpers.py
aerospike_vector_search/shared/base_channel_provider.py
aerospike_vector_search/shared/client_helpers.py
aerospike_vector_search/shared/conversions.py
aerospike_vector_search/shared/helpers.py
aerospike_vector_search/shared/token_manager.py
aerospike_vector_search/shared/proto_generated/auth_pb2.py
aerospike_vector_search/shared/proto_generated/auth_pb2_grpc.py
aerospike_vector_search/shared/proto_generated/index_pb2.py
aerospike_vector_search/shared/proto_generated/index_pb2_grpc.py
aerospike_vector_search/shared/proto_generated/transact_pb2.py
aerospike_vector_search/shared/proto_generated/transact_pb2_grpc.py
aerospike_vector_search/shared/proto_generated/types_pb2.py
aerospike_vector_search/shared/proto_generated/types_pb2_grpc.py
aerospike_vector_search/shared/proto_generated/user_admin_pb2.py
aerospike_vector_search/shared/proto_generated/user_admin_pb2_grpc.py
aerospike_vector_search/shared/proto_generated/vector_db_pb2.py
aerospike_vector_search/shared/proto_generated/vector_db_pb2_grpc.py
aerospike_vector_search-4.2.0.dist-info/licenses/LICENSE
aerospike_vector_search-4.2.0.dist-info/METADATA
aerospike_vector_search-4.2.0.dist-info/WHEEL
aerospike_vector_search-4.2.0.dist-info/top_level.txt
aerospike_vector_search-4.2.0.dist-info/RECORD
